[
    {
        "id": 17892873778916577,
        "created_at": 1616953937,
        "text": "\ud83d\ude0d\ud83d\ude0d\ud83d\ude0d",
        "owner": {
            "id": "6247662406",
            "is_verified": false,
            "profile_pic_url": "https://scontent-lga3-2.cdninstagram.com/v/t51.2885-19/s150x150/141394901_223984549437488_4932682570430060731_n.jpg?tp=1&_nc_ht=scontent-lga3-2.cdninstagram.com&_nc_ohc=jsBP3GFFefcAX_w5jBa&ccb=7-4&oh=6b072d1d480ee7e6784cd68c05f69bd9&oe=608C411D&_nc_sid=9fb510",
            "username": "marika_ferraioli"
        },
        "likes_count": 0,
        "answers": []
    },
    {
        "id": 17855579219517743,
        "created_at": 1616937364,
        "text": "@hollykiim",
        "owner": {
            "id": "4051857867",
            "is_verified": false,
            "profile_pic_url": "https://scontent-lga3-2.cdninstagram.com/v/t51.2885-19/s150x150/155855686_103981251678978_4458851909830462852_n.jpg?tp=1&_nc_ht=scontent-lga3-2.cdninstagram.com&_nc_ohc=Dc2_E2P1X1wAX_vq98P&ccb=7-4&oh=b4c6604d509e92f80fd321a4ec0541a6&oe=608C51BF&_nc_sid=9fb510",
            "username": "dailydiaryforus"
        },
        "likes_count": 0,
        "answers": []
    },
    {
        "id": 17912995294661174,
        "created_at": 1616935265,
        "text": "Omg so beautiful \ud83d\ude0d",
        "owner": {
            "id": "44717809957",
            "is_verified": false,
            "profile_pic_url": "https://scontent-arn2-1.cdninstagram.com/v/t51.2885-19/44884218_345707102882519_2446069589734326272_n.jpg?_nc_ht=scontent-arn2-1.cdninstagram.com&_nc_ohc=mhDR9_0DpXIAX9V7Cs9&ccb=7-4&oh=35394ea3e99bd3fd7e73637d3d598abd&oe=608B680F&_nc_sid=712cc3&ig_cache_key=YW5vbnltb3VzX3Byb2ZpbGVfcGlj.2-ccb7-4",
            "username": "perfectpinkhome"
        },
        "likes_count": 0,
        "answers": []
    },
    {
        "id": 17848998410541394,
        "created_at": 1616923715,
        "text": "\ud83d\ude0d",
        "owner": {
            "id": "6305910880",
            "is_verified": false,
            "profile_pic_url": "https://scontent-lga3-2.cdninstagram.com/v/t51.2885-19/s150x150/153798569_2864661030414651_429971669932164946_n.jpg?tp=1&_nc_ht=scontent-lga3-2.cdninstagram.com&_nc_ohc=f0IUoxs68ukAX99PAOG&ccb=7-4&oh=894852879776faa09e08e80f1a98d91c&oe=608C21BB&_nc_sid=9fb510",
            "username": "rdv_avec_charly"
        },
        "likes_count": 0,
        "answers": []
    },
    {
        "id": 17848932422542664,
        "created_at": 1616895255,
        "text": "Absolutely stunning!!",
        "owner": {
            "id": "32450939327",
            "is_verified": false,
            "profile_pic_url": "https://scontent-lga3-2.cdninstagram.com/v/t51.2885-19/s150x150/146771784_261134085611392_3577975587268732108_n.jpg?tp=1&_nc_ht=scontent-lga3-2.cdninstagram.com&_nc_ohc=YNJOMNLKWewAX9m5xuf&ccb=7-4&oh=29fce2d8eee0520a80ed4aae6afa82d4&oe=608C528D&_nc_sid=9fb510",
            "username": "tammyhawleyh"
        },
        "likes_count": 0,
        "answers": []
    },
    {
        "id": 18140648059194729,
        "created_at": 1616890397,
        "text": "1\ud83c\udf37\ud83d\ude0d",
        "owner": {
            "id": "1706105490",
            "is_verified": false,
            "profile_pic_url": "https://scontent-lga3-2.cdninstagram.com/v/t51.2885-19/s150x150/163804601_479858849721099_6047836122022608959_n.jpg?tp=1&_nc_ht=scontent-lga3-2.cdninstagram.com&_nc_ohc=ooGbiJYDRL0AX_Fk2R6&ccb=7-4&oh=7731df9c0e70771db65705baac76044c&oe=60894A7D&_nc_sid=9fb510",
            "username": "_wing___________"
        },
        "likes_count": 0,
        "answers": []
    },
    {
        "id": 17873488169264959,
        "created_at": 1616873062,
        "text": "\u041d\u0438\u043a\u043e\u0433\u0434\u0430 \u0432 \u0436\u0438\u0432\u0443\u044e \u043d\u0435 \u0432\u0438\u0434\u0435\u043b\u0430 \u0440\u043e\u0437\u043e\u0432\u044b\u0435 \u0442\u044e\u043b\u044c\u043f\u0430\u043d\u044b \u0442\u0430\u043a\u0438\u0435 \u043a\u0440\u0430\u0441\u0438\u0432\u044b\u0435 \ud83d\ude0d",
        "owner": {
            "id": "1677781935",
            "is_verified": false,
            "profile_pic_url": "https://scontent-lga3-2.cdninstagram.com/v/t51.2885-19/s150x150/122616721_140354237820459_3250937801069778615_n.jpg?tp=1&_nc_ht=scontent-lga3-2.cdninstagram.com&_nc_ohc=9p-MjbYBK0IAX_ifNmj&ccb=7-4&oh=b3607c877f733dfed740c889541163ea&oe=608C71D6&_nc_sid=9fb510",
            "username": "emiliasposa.kz"
        },
        "likes_count": 0,
        "answers": []
    },
    {
        "id": 17926103110537623,
        "created_at": 1616872382,
        "text": "Fresh cut flowers are the best.",
        "owner": {
            "id": "2150963445",
            "is_verified": false,
            "profile_pic_url": "https://scontent-arn2-1.cdninstagram.com/v/t51.2885-19/44884218_345707102882519_2446069589734326272_n.jpg?_nc_ht=scontent-arn2-1.cdninstagram.com&_nc_ohc=mhDR9_0DpXIAX9V7Cs9&ccb=7-4&oh=35394ea3e99bd3fd7e73637d3d598abd&oe=608B680F&_nc_sid=712cc3&ig_cache_key=YW5vbnltb3VzX3Byb2ZpbGVfcGlj.2-ccb7-4",
            "username": "north_of_the_border._"
        },
        "likes_count": 0,
        "answers": []
    },
    {
        "id": 18170421568108896,
        "created_at": 1616866876,
        "text": "1",
        "owner": {
            "id": "1423101496",
            "is_verified": false,
            "profile_pic_url": "https://scontent-lga3-2.cdninstagram.com/v/t51.2885-19/s150x150/84223007_221941328805845_7067646758930612224_n.jpg?tp=1&_nc_ht=scontent-lga3-2.cdninstagram.com&_nc_ohc=GR-eCzHCfeUAX9sIIq7&ccb=7-4&oh=35a34b93a11f686bf996855507f68e25&oe=60899562&_nc_sid=9fb510",
            "username": "loora_gomes"
        },
        "likes_count": 0,
        "answers": []
    },
    {
        "id": 18114773497206805,
        "created_at": 1616866681,
        "text": "3",
        "owner": {
            "id": "2908638729",
            "is_verified": false,
            "profile_pic_url": "https://scontent-lga3-2.cdninstagram.com/v/t51.2885-19/s150x150/138950730_1078025105955147_3133183627438801112_n.jpg?tp=1&_nc_ht=scontent-lga3-2.cdninstagram.com&_nc_ohc=8-1vkkM4VG4AX9bt0qR&ccb=7-4&oh=f5cf2b44b520aa47555b093bb362cdc7&oe=608BD0C0&_nc_sid=9fb510",
            "username": "p.c.m1981"
        },
        "likes_count": 0,
        "answers": []
    },
    {
        "id": 17891015453009280,
        "created_at": 1616863158,
        "text": "Love me some tulips! \u2764\ufe0f",
        "owner": {
            "id": "9849779512",
            "is_verified": false,
            "profile_pic_url": "https://scontent-lga3-2.cdninstagram.com/v/t51.2885-19/s150x150/148203115_461020598590652_6159009748106377523_n.jpg?tp=1&_nc_ht=scontent-lga3-2.cdninstagram.com&_nc_ohc=XBXSnMSaEZoAX9-sV-x&ccb=7-4&oh=eafcc187dd5c15332c1b4ad09b640a39&oe=608C1112&_nc_sid=9fb510",
            "username": "gloriatrudystephens"
        },
        "likes_count": 0,
        "answers": []
    },
    {
        "id": 18103735903217086,
        "created_at": 1616860548,
        "text": "4",
        "owner": {
            "id": "7793942503",
            "is_verified": false,
            "profile_pic_url": "https://scontent-lga3-2.cdninstagram.com/v/t51.2885-19/s150x150/123011714_1255328481532688_7915103657280579697_n.jpg?tp=1&_nc_ht=scontent-lga3-2.cdninstagram.com&_nc_ohc=oJodWFx0i4sAX8xWJm0&ccb=7-4&oh=a9a8067b89de0b1cfc458c9ff9879693&oe=6088B2C7&_nc_sid=9fb510",
            "username": "rflifechanger"
        },
        "likes_count": 0,
        "answers": []
    },
    {
        "id": 17925877135540820,
        "created_at": 1616858204,
        "text": "\ud83d\ude0d\ud83d\ude0d\ud83d\ude0d",
        "owner": {
            "id": "3279066879",
            "is_verified": false,
            "profile_pic_url": "https://scontent-lga3-2.cdninstagram.com/v/t51.2885-19/s150x150/54247265_406827686786086_6677827164844326912_n.jpg?tp=1&_nc_ht=scontent-lga3-2.cdninstagram.com&_nc_ohc=oUwvEn5jgL0AX_RMoD2&ccb=7-4&oh=7325bc99bcffa2c7fb52e0f36cd7b064&oe=6089B1E6&_nc_sid=9fb510",
            "username": "para_thai"
        },
        "likes_count": 0,
        "answers": []
    },
    {
        "id": 18005867587308420,
        "created_at": 1616858098,
        "text": "5",
        "owner": {
            "id": "505735319",
            "is_verified": false,
            "profile_pic_url": "https://scontent-lga3-2.cdninstagram.com/v/t51.2885-19/s150x150/153264359_253131379640946_6574521240863315135_n.jpg?tp=1&_nc_ht=scontent-lga3-2.cdninstagram.com&_nc_ohc=ICOQ2lwvYaIAX-6kdZu&ccb=7-4&oh=93dbbaed0b5fe930c83d7b8fb3ddabeb&oe=608B1434&_nc_sid=9fb510",
            "username": "shrinksnightmare"
        },
        "likes_count": 0,
        "answers": []
    },
    {
        "id": 17871856649300669,
        "created_at": 1616856078,
        "text": "First and the last \u2764\ufe0f\u2764\ufe0f\ud83d\ude0d",
        "owner": {
            "id": "1433943177",
            "is_verified": false,
            "profile_pic_url": "https://scontent-lga3-2.cdninstagram.com/v/t51.2885-19/s150x150/106915776_589401418445420_2593345334247743209_n.jpg?tp=1&_nc_ht=scontent-lga3-2.cdninstagram.com&_nc_ohc=_fl2BdvCpTQAX-hAy3i&ccb=7-4&oh=ec6ff707da5cf28e57c3872ac2195ce2&oe=608AAA8C&_nc_sid=9fb510",
            "username": "ceezeeb"
        },
        "likes_count": 0,
        "answers": []
    },
    {
        "id": 17892293029996844,
        "created_at": 1616854729,
        "text": "All of them beautiful \ud83d\ude0d\u2764\ufe0flove it",
        "owner": {
            "id": "41717353640",
            "is_verified": false,
            "profile_pic_url": "https://scontent-lga3-2.cdninstagram.com/v/t51.2885-19/s150x150/160650174_1182711982183315_7942170410624832645_n.jpg?tp=1&_nc_ht=scontent-lga3-2.cdninstagram.com&_nc_ohc=1aO3K9wWgYgAX_vZA_K&ccb=7-4&oh=70039fdf23c42a63651edf9850d95c14&oe=6089E6CA&_nc_sid=9fb510",
            "username": "goldsmith2436_"
        },
        "likes_count": 0,
        "answers": []
    },
    {
        "id": 18099180190240787,
        "created_at": 1616854569,
        "text": "I love them all \u2764\ufe0f\u2764\ufe0f\u2764\ufe0f\u2764\ufe0f\u2764\ufe0f",
        "owner": {
            "id": "6274665",
            "is_verified": false,
            "profile_pic_url": "https://scontent-lga3-2.cdninstagram.com/v/t51.2885-19/s150x150/50775492_1449760635181321_8674554845119643648_n.jpg?tp=1&_nc_ht=scontent-lga3-2.cdninstagram.com&_nc_ohc=0_B7YbisYJgAX-tleaP&ccb=7-4&oh=6dd404781af31ef11db5d913bca116ed&oe=608B623F&_nc_sid=9fb510",
            "username": "charli74"
        },
        "likes_count": 0,
        "answers": []
    },
    {
        "id": 17908507354736681,
        "created_at": 1616854273,
        "text": "\u2764\ufe0f",
        "owner": {
            "id": "38280161121",
            "is_verified": false,
            "profile_pic_url": "https://scontent-lga3-2.cdninstagram.com/v/t51.2885-19/s150x150/106254796_681197776054930_6565659217023962531_n.jpg?tp=1&_nc_ht=scontent-lga3-2.cdninstagram.com&_nc_ohc=FW8PUkCi1v8AX-M4u-T&ccb=7-4&oh=0f1349532be451e59dd7262c4f4ae789&oe=608A1052&_nc_sid=9fb510",
            "username": "bonpers"
        },
        "likes_count": 0,
        "answers": []
    },
    {
        "id": 17866180673430978,
        "created_at": 1616853806,
        "text": "\u2764\ufe0f\u2764\ufe0f",
        "owner": {
            "id": "192703280",
            "is_verified": false,
            "profile_pic_url": "https://scontent-lga3-2.cdninstagram.com/v/t51.2885-19/s150x150/163154606_343613057079131_6879223404188135993_n.jpg?tp=1&_nc_ht=scontent-lga3-2.cdninstagram.com&_nc_ohc=UDMjVF2uFDAAX8XzAOY&ccb=7-4&oh=59f36857ff3860869198c2d36f1dd003&oe=608A9835&_nc_sid=9fb510",
            "username": "thomaskat_72"
        },
        "likes_count": 0,
        "answers": []
    },
    {
        "id": 18208962958060874,
        "created_at": 1616852117,
        "text": "\u2764\ufe0f\u2764\ufe0f\u2764\ufe0f",
        "owner": {
            "id": "2283445925",
            "is_verified": false,
            "profile_pic_url": "https://scontent-lga3-2.cdninstagram.com/v/t51.2885-19/s150x150/162716634_930312737754496_6969186209365163685_n.jpg?tp=1&_nc_ht=scontent-lga3-2.cdninstagram.com&_nc_ohc=iAMeOJVFQ4IAX_GMqM8&tn=CpnMwFJ548VjO17j&ccb=7-4&oh=504e6a6f8cc3e75193fd12dfbd720d34&oe=608BB935&_nc_sid=9fb510",
            "username": "londondiamonddealer"
        },
        "likes_count": 0,
        "answers": []
    },
    {
        "id": 17878372655244052,
        "created_at": 1616850797,
        "text": "2-3",
        "owner": {
            "id": "7830653399",
            "is_verified": false,
            "profile_pic_url": "https://scontent-lga3-2.cdninstagram.com/v/t51.2885-19/s150x150/150303674_430150838219949_3545530651445597918_n.jpg?tp=1&_nc_ht=scontent-lga3-2.cdninstagram.com&_nc_ohc=xnA7QYgjp3gAX9UgC8n&ccb=7-4&oh=ad6f1c0e1af27969df75e0e81e2128b5&oe=608B8758&_nc_sid=9fb510",
            "username": "patisserie_baking"
        },
        "likes_count": 1,
        "answers": []
    },
    {
        "id": 17861646641507093,
        "created_at": 1616850732,
        "text": "1",
        "owner": {
            "id": "213824276",
            "is_verified": false,
            "profile_pic_url": "https://scontent-lga3-2.cdninstagram.com/v/t51.2885-19/s150x150/164884253_3762794923775609_1409131197746734869_n.jpg?tp=1&_nc_ht=scontent-lga3-2.cdninstagram.com&_nc_ohc=jibQDKubbu0AX-gP2UT&ccb=7-4&oh=ad38a567f1544625e21a0df1d02d9134&oe=6089A6D7&_nc_sid=9fb510",
            "username": "nikkilaine89"
        },
        "likes_count": 1,
        "answers": []
    }
]